LICENSE
MANIFEST.in
README.md
README.rst
setup.py
lf_backup/__init__.py
lf_backup/lf-backup
lf_backup/lfbackup.py
lf_backup/lflib.py
lf_backup.egg-info/PKG-INFO
lf_backup.egg-info/SOURCES.txt
lf_backup.egg-info/dependency_links.txt
lf_backup.egg-info/entry_points.txt
lf_backup.egg-info/requires.txt
lf_backup.egg-info/top_level.txt